{
    "room": "Discord Dungeons",
    "author": "Snazzah",
    "icon": "https://cdn.jsdelivr.net/gh/DiscordDungeons/pdjrsc/dddj.png",
    "css": "https://cdn.jsdelivr.net/gh/DiscordDungeons/pdjrsc/main.css",
    "rules": {
        "allowAutorespond": true,
        "allowAutowoot": true,
        "allowAutojoin": true,
        "allowAutograb": true,
        "allowSmartVote": true,
        "allowEmotes": true,
        "allowShowingMehs": true,
        "forceSmartVote": false
    },
    "ccc": {
        "admin": null,
        "ambassador": "#FF8C00",
        "host": "#e32524",
        "cohost": "#e32524",
        "manager": null,
        "bouncer": "#ff7e00",
        "rdj": "#f8b500",
        "subscriber": null,
        "silversubscriber": null,
        "friend": null,
        "user": null
    },
    "images": {
        "background": "https://cdn.radiant.dj/rcs/bg/2k15island.jpg",
        "playback": "https://cdn.jsdelivr.net/gh/DiscordDungeons/pdjrsc/playback.png",
        "admin": null,
        "ambassador": null,
        "host": "https://cdn.jsdelivr.net/gh/DiscordDungeons/pdjrsc/host.png",
        "cohost": "https://cdn.jsdelivr.net/gh/DiscordDungeons/pdjrsc/host.png",
        "manager": null,
        "bouncer": "https://cdn.jsdelivr.net/gh/DiscordDungeons/pdjrsc/manager.png",
        "rdj": "https://cdn.jsdelivr.net/gh/DiscordDungeons/pdjrsc/dj.png",
        "subscriber": null,
        "silversubscriber": null
    },
    "emotes": {
    	"dd": "https://cdn.jsdelivr.net/gh/DiscordDungeons/pdjrsc/icon.png",
    	"dddj": "https://cdn.jsdelivr.net/gh/DiscordDungeons/pdjrsc/dddj.png",
    	"woot": "https://cdn.jsdelivr.net/gh/DiscordDungeons/pdjrsc/woot.png",
    	"meh": "https://cdn.jsdelivr.net/gh/DiscordDungeons/pdjrsc/meh.png",
    	"grab": "https://cdn.jsdelivr.net/gh/DiscordDungeons/pdjrsc/grab.png"
    }
}
